work_wechat_log/__init__.py
work_wechat_log/consts.py
work_wechat_log/log.py
work_wechat_request/__init__.py
work_wechat_request/consts.py
work_wechat_request/request.py
work_wechat_log_notify-0.2.6.dist-info/LICENSE
work_wechat_log_notify-0.2.6.dist-info/METADATA
work_wechat_log_notify-0.2.6.dist-info/WHEEL
work_wechat_log_notify-0.2.6.dist-info/top_level.txt
work_wechat_log_notify-0.2.6.dist-info/RECORD
