Metadata-Version: 2.1
Name: work-wechat-log-notify
Version: 0.2.6
Summary: Work wechat log notify.
Home-page: https://gitee.com/temporary-worker-team/work_wechat_log_notify
Author: kingsword09
License: MIT
Project-URL: Documentation, https://gitee.com/temporary-worker-team/work_wechat_log_notify
Project-URL: Source, https://gitee.com/temporary-worker-team/work_wechat_log_notify
License-File: LICENSE
Requires-Dist: requests
Requires-Dist: tabulate
Requires-Dist: matplotlib
